funf/__func_fibbnacci.py
funf/__func_gcd.py
funf/__init__.py
funf/function.py
funf-0.1.1.dist-info/LICENSE.txt
funf-0.1.1.dist-info/METADATA
funf-0.1.1.dist-info/WHEEL
funf-0.1.1.dist-info/top_level.txt
funf-0.1.1.dist-info/RECORD
