Metadata-Version: 2.1
Name: funf
Version: 0.1.1
Summary: Useful tools and functions in Python
Home-page: UNKNOWN
Author: Ashvini Jangid
Author-email: ashvinijangid@gmail.com
License: MIT
Keywords: func,Gcd,funcs
Platform: UNKNOWN
